ftdc_tools/__init__.py
ftdc_tools/decode.py
ftdc_tools/rollups/__init__.py
ftdc_tools/rollups/client_perf.py
ftdc_tools-0.5.0.dist-info/WHEEL
ftdc_tools-0.5.0.dist-info/METADATA
ftdc_tools-0.5.0.dist-info/RECORD
